{"key": "lep_pt", "true_int": 0}
{"key": "lep_conePt", "true_int": 0}
{"key": "lep_eta", "true_int": 0}
{"key": "lep_tth_mva", "true_int": 0}
{"key": "lep_phi", "true_int": 0}
{"key": "tau1_pt", "true_int": 0}
{"key": "tau1_eta", "true_int": 0}
{"key": "tau1_raw", "true_int": 0}
{"key": "tau1_phi", "true_int": 0}
{"key": "tau2_pt", "true_int": 0}
{"key": "tau2_eta", "true_int": 0}
{"key": "tau2_raw", "true_int": 0}
{"key": "tau2_phi", "true_int": 0}
{"key": "tau3_pt", "true_int": 0}
{"key": "tau3_eta", "true_int": 0}
{"key": "tau3_raw", "true_int": 0}
{"key": "tau3_phi", "true_int": 0}
{"key": "met", "true_int": 0}
{"key": "mht", "true_int": 0}
{"key": "met_LD", "true_int": 0}
{"key": "HT", "true_int": 0}
{"key": "STMET", "true_int": 0}
{"key": "met_phi", "true_int": 0}
{"key": "diHiggsVisMass", "true_int": 0}
{"key": "diHiggsMass", "true_int": 0}
{"key": "nJet", "true_int": 1}
{"key": "nElectron", "true_int": 1}
{"key": "nMuon", "true_int": 1}
{"key": "gen_mHH", "true_int": 1}